Workbook

Sheet Transactions
A1: Date | B1: Description | C1: Amount | D1: Category | E1: Month

Sheet Budget
A1: Category | B1: Monthly Budget
A2: Rent/Mortgage | B2: 0
A3: Utilities | B3: 0
A4: Internet/Phone | B4: 0
A5: Subscriptions | B5: 0
A6: Insurance | B6: 0
A7: Groceries | B7: 0
A8: Eating Out | B8: 0
A9: Transport | B9: 0
A10: Shopping | B10: 0
A11: Health | B11: 0
A12: Debt Payment | B12: 0
A13: Savings | B13: 0
... A19: Travel | B19: 0

Sheet Dashboard
A1: Selected Period: | B1: All | E1: Use the dropdown in B1 to choose a month or All
A3: Key Metrics
A4: Total Income | B4: =IF($B$1="All",SUMIFS(Transactions!$C:$C,Transactions!$C:$C,">0",Transactions!$D:$D,"<>Transfers"),SUMIFS(Transactions!$C:$C,Transactions!$E:$E,$B$1,Transactions!$C:$C,">0",Transactions!$D:$D,"<>Transfers"))
A5: Total Spending | B5: =IF($B$1="All",ABS(SUMIFS(Transactions!$C:$C,Transactions!$C:$C,"<0",Transactions!$D:$D,"<>Transfers")),ABS(SUMIFS(Transactions!$C:$C,Transactions!$E:$E,$B$1,Transactions!$C:$C,"<0",Transactions!$D:$D,"<>Transfers")))
A6: Net Cashflow | B6: =B4-B5
A7: Savings Rate | B7: =IFERROR(B6/B4,0)
A9: Review
A10: Uncategorized Spend | B10: =IF($B$1="All",ABS(SUMIFS(Transactions!$C:$C,Transactions!$C:$C,"<0",Transactions!$D:$D,"Uncategorized")),ABS(SUMIFS(Transactions!$C:$C,Transactions!$E:$E,$B$1,Transactions!$C:$C,"<0",Transactions!$D:$D,"Uncategorized")))
A11: Uncategorized Count | B11: =IF($B$1="All",COUNTIFS(Transactions!$C:$C,"<0",Transactions!$D:$D,"Uncategorized"),COUNTIFS(Transactions!$E:$E,$B$1,Transactions!$C:$C,"<0",Transactions!$D:$D,"Uncategorized"))
A13: Transfers
A14: Transfer In | B14: =IF($B$1="All",SUMIFS(Transactions!$C:$C,Transactions!$C:$C,">0",Transactions!$D:$D,"Transfers"),SUMIFS(Transactions!$C:$C,Transactions!$E:$E,$B$1,Transactions!$C:$C,">0",Transactions!$D:$D,"Transfers"))
A15: Transfer Out | B15: =IF($B$1="All",ABS(SUMIFS(Transactions!$C:$C,Transactions!$C:$C,"<0",Transactions!$D:$D,"Transfers")),ABS(SUMIFS(Transactions!$C:$C,Transactions!$E:$E,$B$1,Transactions!$C:$C,"<0",Transactions!$D:$D,"Transfers")))
A16: Net Transfers | B16: =B14-B15
A18: Budget vs Actual (Spending)
A19: Category | B19: Budget | C19: Actual | D19: Difference | E19: Status
A20: Rent/Mortgage | B20: =IFERROR(VLOOKUP(A20,Budget!$A:$B,2,FALSE),0) | C20: =IF($B$1="All",ABS(SUMIFS(Transactions!$C:$C,Transactions!$D:$D,A20,Transactions!$C:$C,"<0")),ABS(SUMIFS(Transactions!$C:$C,Transactions!$D:$D,A20,Transactions!$E:$E,$B$1,Transactions!$C:$C,"<0"))) | D20: =B20-C20 | E20: =IF(D20<0,"Over Budget","OK")
A21: Utilities | B21: =IFERROR(VLOOKUP(A21,Budget!$A:$B,2,FALSE),0) | C21: =IF($B$1="All",ABS(SUMIFS(Transactions!$C:$C,Transactions!$D:$D,A21,Transactions!$C:$C,"<0")),ABS(SUMIFS(Transactions!$C:$C,Transactions!$D:$D,A21,Transactions!$E:$E,$B$1,Transactions!$C:$C,"<0"))) | D21: =B21-C21 | E21: =IF(D21<0,"Over Budget","OK")
A22: Internet/Phone | B22: =IFERROR(VLOOKUP(A22,Budget!$A:$B,2,FALSE),0) | C22: =IF($B$1="All",ABS(SUMIFS(Transactions!$C:$C,Transactions!$D:$D,A22,Transactions!$C:$C,"<0")),ABS(SUMIFS(Transactions!$C:$C,Transactions!$D:$D,A22,Transactions!$E:$E,$B$1,Transactions!$C:$C,"<0"))) | D22: =B22-C22 | E22: =IF(D22<0,"Over Budget","OK")
A23: Subscriptions | B23: =IFERROR(VLOOKUP(A23,Budget!$A:$B,2,FALSE),0) | C23: =IF($B$1="All",ABS(SUMIFS(Transactions!$C:$C,Transactions!$D:$D,A23,Transactions!$C:$C,"<0")),ABS(SUMIFS(Transactions!$C:$C,Transactions!$D:$D,A23,Transactions!$E:$E,$B$1,Transactions!$C:$C,"<0"))) | D23: =B23-C23 | E23: =IF(D23<0,"Over Budget","OK")
A24: Insurance | B24: =IFERROR(VLOOKUP(A24,Budget!$A:$B,2,FALSE),0) | C24: =IF($B$1="All",ABS(SUMIFS(Transactions!$C:$C,Transactions!$D:$D,A24,Transactions!$C:$C,"<0")),ABS(SUMIFS(Transactions!$C:$C,Transactions!$D:$D,A24,Transactions!$E:$E,$B$1,Transactions!$C:$C,"<0"))) | D24: =B24-C24 | E24: =IF(D24<0,"Over Budget","OK")
A25: Groceries | B25: =IFERROR(VLOOKUP(A25,Budget!$A:$B,2,FALSE),0) | C25: =IF($B$1="All",ABS(SUMIFS(Transactions!$C:$C,Transactions!$D:$D,A25,Transactions!$C:$C,"<0")),ABS(SUMIFS(Transactions!$C:$C,Transactions!$D:$D,A25,Transactions!$E:$E,$B$1,Transactions!$C:$C,"<0"))) | D25: =B25-C25 | E25: =IF(D25<0,"Over Budget","OK")
A26: Eating Out | B26: =IFERROR(VLOOKUP(A26,Budget!$A:$B,2,FALSE),0) | C26: =IF($B$1="All",ABS(SUMIFS(Transactions!$C:$C,Transactions!$D:$D,A26,Transactions!$C:$C,"<0")),ABS(SUMIFS(Transactions!$C:$C,Transactions!$D:$D,A26,Transactions!$E:$E,$B$1,Transactions!$C:$C,"<0"))) | D26: =B26-C26 | E26: =IF(D26<0,"Over Budget","OK")
A27: Transport | B27: =IFERROR(VLOOKUP(A27,Budget!$A:$B,2,FALSE),0) | C27: =IF($B$1="All",ABS(SUMIFS(Transactions!$C:$C,Transactions!$D:$D,A27,Transactions!$C:$C,"<0")),ABS(SUMIFS(Transactions!$C:$C,Transactions!$D:$D,A27,Transactions!$E:$E,$B$1,Transactions!$C:$C,"<0"))) | D27: =B27-C27 | E27: =IF(D27<0,"Over Budget","OK")
A28: Shopping | B28: =IFERROR(VLOOKUP(A28,Budget!$A:$B,2,FALSE),0) | C28: =IF($B$1="All",ABS(SUMIFS(Transactions!$C:$C,Transactions!$D:$D,A28,Transactions!$C:$C,"<0")),ABS(SUMIFS(Transactions!$C:$C,Transactions!$D:$D,A28,Transactions!$E:$E,$B$1,Transactions!$C:$C,"<0"))) | D28: =B28-C28 | E28: =IF(D28<0,"Over Budget","OK")
A29: Health | B29: =IFERROR(VLOOKUP(A29,Budget!$A:$B,2,FALSE),0) | C29: =IF($B$1="All",ABS(SUMIFS(Transactions!$C:$C,Transactions!$D:$D,A29,Transactions!$C:$C,"<0")),ABS(SUMIFS(Transactions!$C:$C,Transactions!$D:$D,A29,Transactions!$E:$E,$B$1,Transactions!$C:$C,"<0"))) | D29: =B29-C29 | E29: =IF(D29<0,"Over Budget","OK")
A30: Debt Payment | B30: =IFERROR(VLOOKUP(A30,Budget!$A:$B,2,FALSE),0) | C30: =IF($B$1="All",ABS(SUMIFS(Transactions!$C:$C,Transactions!$D:$D,A30,Transactions!$C:$C,"<0")),ABS(SUMIFS(Transactions!$C:$C,Transactions!$D:$D,A30,Transactions!$E:$E,$B$1,Transactions!$C:$C,"<0"))) | D30: =B30-C30 | E30: =IF(D30<0,"Over Budget","OK")
A31: Savings | B31: =IFERROR(VLOOKUP(A31,Budget!$A:$B,2,FALSE),0) | C31: =IF($B$1="All",ABS(SUMIFS(Transactions!$C:$C,Transactions!$D:$D,A31,Transactions!$C:$C,"<0")),ABS(SUMIFS(Transactions!$C:$C,Transactions!$D:$D,A31,Transactions!$E:$E,$B$1,Transactions!$C:$C,"<0"))) | D31: =B31-C31 | E31: =IF(D31<0,"Over Budget","OK")
... A37: Travel | B37: =IFERROR(VLOOKUP(A37,Budget!$A:$B,2,FALSE),0) | C37: =IF($B$1="All",ABS(SUMIFS(Transactions!$C:$C,Transactions!$D:$D,A37,Transactions!$C:$C,"<0")),ABS(SUMIFS(Transactions!$C:$C,Transactions!$D:$D,A37,Transactions!$E:$E,$B$1,Transactions!$C:$C,"<0"))) | D37: =B37-C37 | E37: =IF(D37<0,"Over Budget","OK")

Sheet Uncategorized
A1: Date | B1: Description | C1: Amount | D1: Category | E1: Month

Sheet Periods
A1: Period
A2: All
